{
  "gizmos-infos": {
    "is2D": true,
    "is3DIcon": false,
    "iconSize": 2,
    "gridVisible": false,
    "gridColor": [
      166,
      166,
      166,
      255
    ],
    "transformToolName": "position",
    "pivot": "pivot",
    "coordinate": "local",
    "toolsVisibility3d": true
  },
  "__version__": "1.0.1",
  "builder": {},
  "snap-configs": {
    "position": {
      "x": 6,
      "y": 6,
      "z": 6
    },
    "rotation": 1,
    "scale": 1,
    "isPositionSnapEnabled": false,
    "isRotationSnapEnabled": false,
    "isScaleSnapEnabled": false
  },
  "rect-snap-configs": {
    "enableSnapping": true,
    "snapThreshold": 4
  },
  "float-window": {
    "position": {
      "cc": {
        "Camera": {
          "dock": false,
          "top": null,
          "bottom": 10,
          "left": null,
          "right": 10
        }
      }
    }
  },
  "camera-infos": {
    "0eafc66e-42da-4091-aa45-2c5d342fc468": {
      "position": {
        "x": 960,
        "y": 540,
        "z": 5000
      },
      "rotation": {
        "x": 0,
        "y": 0,
        "z": 0,
        "w": 1
      },
      "viewCenter": {
        "x": 0,
        "y": 0,
        "z": 0
      },
      "contentRect": {
        "x": 0,
        "y": 0,
        "width": 786.4888888888888,
        "height": 442.4
      },
      "scale": 0.4096296296296296
    },
    "cd91b0ba-da08-4b87-b1bb-d0683e31f565": {
      "position": {
        "x": 959.9999999999999,
        "y": 540,
        "z": 5000
      },
      "rotation": {
        "x": 0,
        "y": 0,
        "z": 0,
        "w": 1
      },
      "viewCenter": {
        "x": 0,
        "y": 0,
        "z": 0
      },
      "contentRect": {
        "x": 0,
        "y": 97.65625,
        "width": 1312.5,
        "height": 875
      },
      "scale": 0.7
    },
    "5b5eba9f-98e7-421e-9be5-6ec301d50923": {
      "position": {
        "x": 960.0000000000001,
        "y": 540.1474201474202,
        "z": 5000
      },
      "rotation": {
        "x": 0,
        "y": 0,
        "z": 0,
        "w": 1
      },
      "viewCenter": {
        "x": 0,
        "y": 0,
        "z": 0
      },
      "contentRect": {
        "x": 0.19432314410486082,
        "y": 0,
        "width": 711.9,
        "height": 400.4
      },
      "scale": 0.7
    },
    "612b61ac-1bc8-4841-bf86-e4736e1d5f42": {
      "position": {
        "x": 960.0000000000001,
        "y": 540.1474201474202,
        "z": 5000
      },
      "rotation": {
        "x": 0,
        "y": 0,
        "z": 0,
        "w": 1
      },
      "viewCenter": {
        "x": 0,
        "y": 0,
        "z": 0
      },
      "contentRect": {
        "x": 0.19432314410486082,
        "y": 0,
        "width": 711.9,
        "height": 400.4
      },
      "scale": 0.7
    },
    "9bac4b49-b005-49f9-8157-27618929b962": {
      "position": {
        "x": 945.6708333333335,
        "y": 532.1310851760852,
        "z": 5000
      },
      "rotation": {
        "x": 0,
        "y": 0,
        "z": 0,
        "w": 1
      },
      "viewCenter": {
        "x": 0,
        "y": 0,
        "z": 0
      },
      "contentRect": {
        "x": 0.19432314410486082,
        "y": 0,
        "width": 711.9,
        "height": 400.4
      },
      "scale": 0.7
    },
    "0ec9383c-d39c-4805-a823-2cd6b58878d8": {
      "position": {
        "x": 960,
        "y": 540,
        "z": 5000
      },
      "rotation": {
        "x": 0,
        "y": 0,
        "z": 0,
        "w": 1
      },
      "viewCenter": {
        "x": 0,
        "y": 0,
        "z": 0
      },
      "contentRect": {
        "x": -67.02531645569611,
        "y": 0,
        "width": 786.4888888888888,
        "height": 442.4
      },
      "scale": 0.4096296296296296
    },
    "fd3c3b3f-7f19-4a87-a25d-72cebd8bc638": {
      "position": {
        "x": 943.4083333333335,
        "y": 530.8653480753482,
        "z": 5000
      },
      "rotation": {
        "x": 0,
        "y": 0,
        "z": 0,
        "w": 1
      },
      "viewCenter": {
        "x": 0,
        "y": 0,
        "z": 0
      },
      "contentRect": {
        "x": 0.19432314410486082,
        "y": 0,
        "width": 711.9,
        "height": 400.4
      },
      "scale": 0.7
    },
    "d0e881eb-a10c-4f78-aab0-dbc3172791f8": {
      "position": {
        "x": 735.2583333333334,
        "y": 414.4175348075349,
        "z": 5000
      },
      "rotation": {
        "x": 0,
        "y": 0,
        "z": 0,
        "w": 1
      },
      "viewCenter": {
        "x": 0,
        "y": 0,
        "z": 0
      },
      "contentRect": {
        "x": 0.19432314410486082,
        "y": 0,
        "width": 711.9,
        "height": 400.4
      },
      "scale": 0.7
    },
    "35614269-7628-4e76-85dd-a9853a8446b4": {
      "position": {
        "x": 816.7083333333335,
        "y": 459.98407043407053,
        "z": 5000
      },
      "rotation": {
        "x": 0,
        "y": 0,
        "z": 0,
        "w": 1
      },
      "viewCenter": {
        "x": 0,
        "y": 0,
        "z": 0
      },
      "contentRect": {
        "x": 0.19432314410486082,
        "y": 0,
        "width": 711.9,
        "height": 400.4
      },
      "scale": 0.7
    },
    "1a61f11a-3af2-4364-8260-ed1185732a77": {
      "position": {
        "x": 775.9833333333333,
        "y": 437.2008026208027,
        "z": 5000
      },
      "rotation": {
        "x": 0,
        "y": 0,
        "z": 0,
        "w": 1
      },
      "viewCenter": {
        "x": 0,
        "y": 0,
        "z": 0
      },
      "contentRect": {
        "x": 0.19432314410486082,
        "y": 0,
        "width": 711.9,
        "height": 400.4
      },
      "scale": 0.7
    },
    "cdec76aa-db95-45a9-9a57-a52813ff39d1": {
      "position": {
        "x": 778.2458333333334,
        "y": 438.4665397215398,
        "z": 5000
      },
      "rotation": {
        "x": 0,
        "y": 0,
        "z": 0,
        "w": 1
      },
      "viewCenter": {
        "x": 0,
        "y": 0,
        "z": 0
      },
      "contentRect": {
        "x": 0.19432314410486082,
        "y": 0,
        "width": 711.9,
        "height": 400.4
      },
      "scale": 0.7
    },
    "62e84449-2277-423b-a4b9-e919493698df": {
      "position": {
        "x": 823.4958333333334,
        "y": 463.7812817362818,
        "z": 5000
      },
      "rotation": {
        "x": 0,
        "y": 0,
        "z": 0,
        "w": 1
      },
      "viewCenter": {
        "x": 0,
        "y": 0,
        "z": 0
      },
      "contentRect": {
        "x": 0.19432314410486082,
        "y": 0,
        "width": 711.9,
        "height": 400.4
      },
      "scale": 0.7
    },
    "505e33f0-1e7c-4084-b67e-d964a36c56ce": {
      "position": {
        "x": 818.9708333333335,
        "y": 461.2498075348076,
        "z": 5000
      },
      "rotation": {
        "x": 0,
        "y": 0,
        "z": 0,
        "w": 1
      },
      "viewCenter": {
        "x": 0,
        "y": 0,
        "z": 0
      },
      "contentRect": {
        "x": 0.19432314410486082,
        "y": 0,
        "width": 711.9,
        "height": 400.4
      },
      "scale": 0.7
    },
    "7e5b728a-f008-4e3e-819e-84da9f533a56": {
      "position": {
        "x": 960,
        "y": 540,
        "z": 5000
      },
      "rotation": {
        "x": 0,
        "y": 0,
        "z": 0,
        "w": 1
      },
      "viewCenter": {
        "x": 0,
        "y": 0,
        "z": 0
      },
      "contentRect": {
        "x": -67.02531645569611,
        "y": 0,
        "width": 786.4888888888888,
        "height": 442.4
      },
      "scale": 0.4096296296296296
    },
    "d1c5e9a0-ef86-42af-a253-95c369fd7c6f": {
      "position": {
        "x": 959.9999999999999,
        "y": 540,
        "z": 5000
      },
      "rotation": {
        "x": 0,
        "y": 0,
        "z": 0,
        "w": 1
      },
      "viewCenter": {
        "x": 0,
        "y": 0,
        "z": 0
      },
      "contentRect": {
        "x": 0,
        "y": 97.65625,
        "width": 1312.5,
        "height": 875
      },
      "scale": 0.7
    },
    "97b4fb89-2498-49e4-9723-d9e492ffe568": {
      "position": {
        "x": 960.0000000000001,
        "y": 540.1474201474202,
        "z": 5000
      },
      "rotation": {
        "x": 0,
        "y": 0,
        "z": 0,
        "w": 1
      },
      "viewCenter": {
        "x": 0,
        "y": 0,
        "z": 0
      },
      "contentRect": {
        "x": 0.19432314410486082,
        "y": 0,
        "width": 711.9,
        "height": 400.4
      },
      "scale": 0.7
    },
    "2dc56544-6207-4c34-80ad-aa304fac1c67": {
      "position": {
        "x": 451,
        "y": 253.5,
        "z": 5000
      },
      "rotation": {
        "x": 0,
        "y": 0,
        "z": 0,
        "w": 1
      },
      "viewCenter": {
        "x": 0,
        "y": 0,
        "z": 0
      },
      "contentRect": {
        "x": 0.1945812807882216,
        "y": 0,
        "width": 631.4,
        "height": 354.9
      },
      "scale": 0.7
    },
    "0e053a2d-abc1-4749-bc9b-61934b535eb0": {
      "position": {
        "x": 928.8273399014777,
        "y": 522.3941666666667,
        "z": 5000
      },
      "rotation": {
        "x": 0,
        "y": 0,
        "z": 0,
        "w": 1
      },
      "viewCenter": {
        "x": 0,
        "y": 0,
        "z": 0
      },
      "contentRect": {
        "x": 0.1945812807882216,
        "y": 0,
        "width": 631.4,
        "height": 354.9
      },
      "scale": 0.7
    },
    "c569d17e-70b9-4b6d-bd96-dfc6bbe7771c": {
      "position": {
        "x": 960.2955665024629,
        "y": 540,
        "z": 5000
      },
      "rotation": {
        "x": 0,
        "y": 0,
        "z": 0,
        "w": 1
      },
      "viewCenter": {
        "x": 0,
        "y": 0,
        "z": 0
      },
      "contentRect": {
        "x": 0.1945812807882216,
        "y": 0,
        "width": 631.4,
        "height": 354.9
      },
      "scale": 0.7
    },
    "ed4cc7d3-235c-431e-9614-f7053835c132": {
      "position": {
        "x": 960.2955665024629,
        "y": 540,
        "z": 5000
      },
      "rotation": {
        "x": 0,
        "y": 0,
        "z": 0,
        "w": 1
      },
      "viewCenter": {
        "x": 0,
        "y": 0,
        "z": 0
      },
      "contentRect": {
        "x": 0.1945812807882216,
        "y": 0,
        "width": 631.4,
        "height": 354.9
      },
      "scale": 0.7
    },
    "5db5f5c0-4386-4082-8c4f-f1b5524fdbdd": {
      "position": {
        "x": 451,
        "y": 253.5,
        "z": 5000
      },
      "rotation": {
        "x": 0,
        "y": 0,
        "z": 0,
        "w": 1
      },
      "viewCenter": {
        "x": 0,
        "y": 0,
        "z": 0
      },
      "contentRect": {
        "x": 0.1945812807882216,
        "y": 0,
        "width": 631.4,
        "height": 354.9
      },
      "scale": 0.7
    },
    "ee3ef0fc-86d4-4077-8b0b-dbf8ecdefaed": {
      "position": {
        "x": 960.2955665024629,
        "y": 540,
        "z": 5000
      },
      "rotation": {
        "x": 0,
        "y": 0,
        "z": 0,
        "w": 1
      },
      "viewCenter": {
        "x": 0,
        "y": 0,
        "z": 0
      },
      "contentRect": {
        "x": 0.1945812807882216,
        "y": 0,
        "width": 631.4,
        "height": 354.9
      },
      "scale": 0.7
    },
    "cf1175e4-8324-437c-a420-c2f0f8a70dc2": {
      "position": {
        "x": 862.4889162561576,
        "y": 485.2791666666667,
        "z": 5000
      },
      "rotation": {
        "x": 0,
        "y": 0,
        "z": 0,
        "w": 1
      },
      "viewCenter": {
        "x": 0,
        "y": 0,
        "z": 0
      },
      "contentRect": {
        "x": 0.1945812807882216,
        "y": 0,
        "width": 631.4,
        "height": 354.9
      },
      "scale": 0.7
    },
    "b42782ab-a213-412f-8aec-f1e398f9b4b1": {
      "position": {
        "x": 960.2955665024629,
        "y": 540,
        "z": 5000
      },
      "rotation": {
        "x": 0,
        "y": 0,
        "z": 0,
        "w": 1
      },
      "viewCenter": {
        "x": 0,
        "y": 0,
        "z": 0
      },
      "contentRect": {
        "x": 0.1945812807882216,
        "y": 0,
        "width": 631.4,
        "height": 354.9
      },
      "scale": 0.7
    },
    "db52f545-2e9a-4dc4-a5fa-d3e56f33c118": {
      "position": {
        "x": 451,
        "y": 253.5,
        "z": 5000
      },
      "rotation": {
        "x": 0,
        "y": 0,
        "z": 0,
        "w": 1
      },
      "viewCenter": {
        "x": 0,
        "y": 0,
        "z": 0
      },
      "contentRect": {
        "x": 0.1945812807882216,
        "y": 0,
        "width": 631.4,
        "height": 354.9
      },
      "scale": 0.7
    },
    "80fd569e-e916-4cf2-b59d-04472a659229": {
      "position": {
        "x": 451,
        "y": 253.5,
        "z": 5000
      },
      "rotation": {
        "x": 0,
        "y": 0,
        "z": 0,
        "w": 1
      },
      "viewCenter": {
        "x": 0,
        "y": 0,
        "z": 0
      },
      "contentRect": {
        "x": 0.1945812807882216,
        "y": 0,
        "width": 631.4,
        "height": 354.9
      },
      "scale": 0.7
    },
    "832d6c44-98bc-4d03-85a3-0e561f77935a": {
      "position": {
        "x": 960,
        "y": 540,
        "z": 5000
      },
      "rotation": {
        "x": 0,
        "y": 0,
        "z": 0,
        "w": 1
      },
      "viewCenter": {
        "x": 0,
        "y": 0,
        "z": 0
      },
      "contentRect": {
        "x": 70.33333333333336,
        "y": 0,
        "width": 841.4,
        "height": 417.9
      },
      "scale": 0.7
    },
    "89097882-5158-429f-9ccc-13194e65aa30": {
      "position": {
        "x": 960,
        "y": 540,
        "z": 5000
      },
      "rotation": {
        "x": 0,
        "y": 0,
        "z": 0,
        "w": 1
      },
      "viewCenter": {
        "x": 0,
        "y": 0,
        "z": 0
      },
      "contentRect": {
        "x": 2.5942325698300777e-13,
        "y": -8.685524126455789,
        "width": 841.4000000000001,
        "height": 473.2875000000001
      },
      "scale": 0.4382291666666667
    },
    "a79f85c2-25a5-4082-95ba-d17900b956f6": {
      "position": {
        "x": 959.9999999999999,
        "y": 540,
        "z": 5000
      },
      "rotation": {
        "x": 0,
        "y": 0,
        "z": 0,
        "w": 1
      },
      "viewCenter": {
        "x": 0,
        "y": 0,
        "z": 0
      },
      "contentRect": {
        "x": 0,
        "y": 97.65625,
        "width": 1312.5,
        "height": 875
      },
      "scale": 0.7
    },
    "759baef4-8779-4396-b8a6-e2a5f52f5704": {
      "position": {
        "x": 919.5208333333335,
        "y": 516.215,
        "z": 5000
      },
      "rotation": {
        "x": 0,
        "y": 0,
        "z": 0,
        "w": 1
      },
      "viewCenter": {
        "x": 0,
        "y": 0,
        "z": 0
      },
      "contentRect": {
        "x": 18.944444444444297,
        "y": 0,
        "width": 837.8999999999999,
        "height": 456.4
      },
      "scale": 0.7
    },
    "bbd4e24d-4b1e-4193-b4a8-01fd31d37108": {
      "position": {
        "x": 811.4593596059112,
        "y": 456.72916666666674,
        "z": 5000
      },
      "rotation": {
        "x": 0,
        "y": 0,
        "z": 0,
        "w": 1
      },
      "viewCenter": {
        "x": 0,
        "y": 0,
        "z": 0
      },
      "contentRect": {
        "x": 0.1945812807882216,
        "y": 0,
        "width": 631.4,
        "height": 354.9
      },
      "scale": 0.7
    },
    "06786de6-04bf-48a5-80b2-2d33e1ff5c5f": {
      "position": {
        "x": 760.4298029556649,
        "y": 428.1791666666667,
        "z": 5000
      },
      "rotation": {
        "x": 0,
        "y": 0,
        "z": 0,
        "w": 1
      },
      "viewCenter": {
        "x": 0,
        "y": 0,
        "z": 0
      },
      "contentRect": {
        "x": 0.1945812807882216,
        "y": 0,
        "width": 631.4,
        "height": 354.9
      },
      "scale": 0.7
    },
    "9415fb5f-04f2-42a9-a4b4-fe38287a5b73": {
      "position": {
        "x": 867.5918719211822,
        "y": 488.1341666666667,
        "z": 5000
      },
      "rotation": {
        "x": 0,
        "y": 0,
        "z": 0,
        "w": 1
      },
      "viewCenter": {
        "x": 0,
        "y": 0,
        "z": 0
      },
      "contentRect": {
        "x": 0.1945812807882216,
        "y": 0,
        "width": 631.4,
        "height": 354.9
      },
      "scale": 0.7
    },
    "04d3c826-63fd-4069-bb05-d3df12dc1593": {
      "position": {
        "x": 898.2096059113298,
        "y": 505.2641666666667,
        "z": 5000
      },
      "rotation": {
        "x": 0,
        "y": 0,
        "z": 0,
        "w": 1
      },
      "viewCenter": {
        "x": 0,
        "y": 0,
        "z": 0
      },
      "contentRect": {
        "x": 0.1945812807882216,
        "y": 0,
        "width": 631.4,
        "height": 354.9
      },
      "scale": 0.7
    },
    "b5e31096-9b38-4f51-a969-296c9b331515": {
      "position": {
        "x": 600,
        "y": 342.5,
        "z": 5000
      },
      "rotation": {
        "x": 0,
        "y": 0,
        "z": 0,
        "w": 1
      },
      "viewCenter": {
        "x": 0,
        "y": 0,
        "z": 0
      },
      "contentRect": {
        "x": 149.00000000000003,
        "y": 89.00000000000003,
        "width": 840,
        "height": 479.5
      },
      "scale": 0.7
    },
    "f823666d-c4f7-49cc-9f9b-96e95333ca8a": {
      "position": {
        "x": 762.9812807881772,
        "y": 429.6066666666667,
        "z": 5000
      },
      "rotation": {
        "x": 0,
        "y": 0,
        "z": 0,
        "w": 1
      },
      "viewCenter": {
        "x": 0,
        "y": 0,
        "z": 0
      },
      "contentRect": {
        "x": 0.1945812807882216,
        "y": 0,
        "width": 631.4,
        "height": 354.9
      },
      "scale": 0.7
    },
    "f3a5ecd8-45b8-4103-a5eb-144fdd84347b": {
      "position": {
        "x": 711.9517241379309,
        "y": 401.0566666666667,
        "z": 5000
      },
      "rotation": {
        "x": 0,
        "y": 0,
        "z": 0,
        "w": 1
      },
      "viewCenter": {
        "x": 0,
        "y": 0,
        "z": 0
      },
      "contentRect": {
        "x": 0.1945812807882216,
        "y": 0,
        "width": 631.4,
        "height": 354.9
      },
      "scale": 0.7
    },
    "e537e8a5-4734-4083-9491-cd4b0dd969c9": {
      "position": {
        "x": 829.3197044334975,
        "y": 466.7216666666667,
        "z": 5000
      },
      "rotation": {
        "x": 0,
        "y": 0,
        "z": 0,
        "w": 1
      },
      "viewCenter": {
        "x": 0,
        "y": 0,
        "z": 0
      },
      "contentRect": {
        "x": 0.1945812807882216,
        "y": 0,
        "width": 631.4,
        "height": 354.9
      },
      "scale": 0.7
    },
    "b7dab5bb-bead-4d11-bc11-2d88063fc892": {
      "position": {
        "x": 752.775369458128,
        "y": 423.89666666666665,
        "z": 5000
      },
      "rotation": {
        "x": 0,
        "y": 0,
        "z": 0,
        "w": 1
      },
      "viewCenter": {
        "x": 0,
        "y": 0,
        "z": 0
      },
      "contentRect": {
        "x": 0.1945812807882216,
        "y": 0,
        "width": 631.4,
        "height": 354.9
      },
      "scale": 0.7
    },
    "facf227b-9ed3-479a-99c7-40ae0878c89e": {
      "position": {
        "x": 959.9999999999998,
        "y": 540,
        "z": 5000
      },
      "rotation": {
        "x": 0,
        "y": 0,
        "z": 0,
        "w": 1
      },
      "viewCenter": {
        "x": 0,
        "y": 0,
        "z": 0
      },
      "contentRect": {
        "x": 0,
        "y": 0,
        "width": 445.9,
        "height": 250.81875
      },
      "scale": 0.23223958333333333
    },
    "bc720914-1af9-480f-ae2a-9219b302e395": {
      "position": {
        "x": 959.9999999999999,
        "y": 540,
        "z": 5000
      },
      "rotation": {
        "x": 0,
        "y": 0,
        "z": 0,
        "w": 1
      },
      "viewCenter": {
        "x": 0,
        "y": 0,
        "z": 0
      },
      "contentRect": {
        "x": 0,
        "y": 97.65625,
        "width": 1312.5,
        "height": 875
      },
      "scale": 0.7
    },
    "e847c8d7-2ff0-4a65-9317-1eaab46a0d33": {
      "position": {
        "x": 481.2767561253984,
        "y": 589.7893427710017,
        "z": 5000
      },
      "rotation": {
        "x": 0,
        "y": 0,
        "z": 0,
        "w": 1
      },
      "viewCenter": {
        "x": 0,
        "y": 0,
        "z": 0
      },
      "contentRect": {
        "x": 291.89552306121504,
        "y": 452.1386192094367,
        "width": 840,
        "height": 479.5
      },
      "scale": 1.1772549813552
    },
    "e8a698e9-c3e5-49bb-91d2-499b72e8d112": {
      "position": {
        "x": 959.9999999999999,
        "y": 540,
        "z": 5000
      },
      "rotation": {
        "x": 0,
        "y": 0,
        "z": 0,
        "w": 1
      },
      "viewCenter": {
        "x": 0,
        "y": 0,
        "z": 0
      },
      "contentRect": {
        "x": 0,
        "y": -215.5634427684116,
        "width": 788.9000000000001,
        "height": 443.75625000000014
      },
      "scale": 0.4108854166666668
    },
    "68a4ecd7-5807-4ddd-9ffb-7ec93a352acc": {
      "position": {
        "x": 937.5000000000001,
        "y": 625,
        "z": 5000
      },
      "rotation": {
        "x": 0,
        "y": 0,
        "z": 0,
        "w": 1
      },
      "viewCenter": {
        "x": 0,
        "y": 0,
        "z": 0
      },
      "contentRect": {
        "x": 0,
        "y": 97.65625,
        "width": 1312.5,
        "height": 875
      },
      "scale": 0.7
    },
    "c449f4f8-b438-4b67-89f5-929ca43e93fd": {
      "position": {
        "x": 1655.4213511234561,
        "y": 302.3621606473505,
        "z": 5000
      },
      "rotation": {
        "x": 0,
        "y": 0,
        "z": 0,
        "w": 1
      },
      "viewCenter": {
        "x": 0,
        "y": 0,
        "z": 0
      },
      "contentRect": {
        "x": 1120.4963402051137,
        "y": -118.64802984472546,
        "width": 788.9000000000001,
        "height": 91.7325581395349
      },
      "scale": 0.7373930774386876
    },
    "95e721c7-1969-45d9-ab89-d51a47903335": {
      "position": {
        "x": 962.2979270671696,
        "y": 309.43082368902327,
        "z": 5000
      },
      "rotation": {
        "x": 0,
        "y": 0,
        "z": 0,
        "w": 1
      },
      "viewCenter": {
        "x": 0,
        "y": 0,
        "z": 0
      },
      "contentRect": {
        "x": 299.14727214175355,
        "y": 232.320282418626,
        "width": 788.9000000000001,
        "height": 91.7325581395349
      },
      "scale": 0.5948120492233602
    },
    "fbfe8be4-92d2-4a0c-99c4-ce898c500381": {
      "position": {
        "x": 563.4999999999999,
        "y": 425.99999999999994,
        "z": 5000
      },
      "rotation": {
        "x": 0,
        "y": 0,
        "z": 0,
        "w": 1
      },
      "viewCenter": {
        "x": 0,
        "y": 0,
        "z": 0
      },
      "contentRect": {
        "x": -1.624097681737372e-13,
        "y": 109.03124999999989,
        "width": 788.8999999999999,
        "height": 596.4
      },
      "scale": 0.7
    },
    "ee85a2ca-c728-4e23-a0a3-c11d1f3ed1e0": {
      "position": {
        "x": 563.1926143871154,
        "y": 650.9886323449599,
        "z": 5000
      },
      "rotation": {
        "x": 0,
        "y": 0,
        "z": 0,
        "w": 1
      },
      "viewCenter": {
        "x": 0,
        "y": 0,
        "z": 0
      },
      "contentRect": {
        "x": 216.9371930180253,
        "y": 368.44166016981455,
        "width": 760.9000000000001,
        "height": 88.47674418604653
      },
      "scale": 1.0987553595426893
    },
    "173126b5-beb5-4bfd-a7f2-3494e4553081": {
      "position": {
        "x": 960,
        "y": 540.0000000000001,
        "z": 5000
      },
      "rotation": {
        "x": 0,
        "y": 0,
        "z": 0,
        "w": 1
      },
      "viewCenter": {
        "x": 0,
        "y": 0,
        "z": 0
      },
      "contentRect": {
        "x": -1.624097681737372e-13,
        "y": 120.28124999999993,
        "width": 760.8999999999999,
        "height": 596.4
      },
      "scale": 0.7
    },
    "7eeaa1fc-e949-4eda-aa06-6cd364a2fe85": {
      "position": {
        "x": 848.9143172663362,
        "y": 397.8455991862298,
        "z": 5000
      },
      "rotation": {
        "x": 0,
        "y": 0,
        "z": 0,
        "w": 1
      },
      "viewCenter": {
        "x": 0,
        "y": 0,
        "z": 0
      },
      "contentRect": {
        "x": 46.25930694821849,
        "y": -257.1267965379381,
        "width": 760.9000000000001,
        "height": 620.9000000000001
      },
      "scale": 0.47398944142791255
    }
  },
  "camera-uuids": [
    "0eafc66e-42da-4091-aa45-2c5d342fc468",
    "cd91b0ba-da08-4b87-b1bb-d0683e31f565",
    "5b5eba9f-98e7-421e-9be5-6ec301d50923",
    "612b61ac-1bc8-4841-bf86-e4736e1d5f42",
    "9bac4b49-b005-49f9-8157-27618929b962",
    "0ec9383c-d39c-4805-a823-2cd6b58878d8",
    "fd3c3b3f-7f19-4a87-a25d-72cebd8bc638",
    "d0e881eb-a10c-4f78-aab0-dbc3172791f8",
    "35614269-7628-4e76-85dd-a9853a8446b4",
    "1a61f11a-3af2-4364-8260-ed1185732a77",
    "cdec76aa-db95-45a9-9a57-a52813ff39d1",
    "62e84449-2277-423b-a4b9-e919493698df",
    "505e33f0-1e7c-4084-b67e-d964a36c56ce",
    "7e5b728a-f008-4e3e-819e-84da9f533a56",
    "d1c5e9a0-ef86-42af-a253-95c369fd7c6f",
    "97b4fb89-2498-49e4-9723-d9e492ffe568",
    "2dc56544-6207-4c34-80ad-aa304fac1c67",
    "0e053a2d-abc1-4749-bc9b-61934b535eb0",
    "c569d17e-70b9-4b6d-bd96-dfc6bbe7771c",
    "ed4cc7d3-235c-431e-9614-f7053835c132",
    "5db5f5c0-4386-4082-8c4f-f1b5524fdbdd",
    "ee3ef0fc-86d4-4077-8b0b-dbf8ecdefaed",
    "cf1175e4-8324-437c-a420-c2f0f8a70dc2",
    "b42782ab-a213-412f-8aec-f1e398f9b4b1",
    "db52f545-2e9a-4dc4-a5fa-d3e56f33c118",
    "80fd569e-e916-4cf2-b59d-04472a659229",
    "832d6c44-98bc-4d03-85a3-0e561f77935a",
    "89097882-5158-429f-9ccc-13194e65aa30",
    "a79f85c2-25a5-4082-95ba-d17900b956f6",
    "759baef4-8779-4396-b8a6-e2a5f52f5704",
    "bbd4e24d-4b1e-4193-b4a8-01fd31d37108",
    "06786de6-04bf-48a5-80b2-2d33e1ff5c5f",
    "9415fb5f-04f2-42a9-a4b4-fe38287a5b73",
    "04d3c826-63fd-4069-bb05-d3df12dc1593",
    "b5e31096-9b38-4f51-a969-296c9b331515",
    "f823666d-c4f7-49cc-9f9b-96e95333ca8a",
    "f3a5ecd8-45b8-4103-a5eb-144fdd84347b",
    "e537e8a5-4734-4083-9491-cd4b0dd969c9",
    "b7dab5bb-bead-4d11-bc11-2d88063fc892",
    "facf227b-9ed3-479a-99c7-40ae0878c89e",
    "bc720914-1af9-480f-ae2a-9219b302e395",
    "e847c8d7-2ff0-4a65-9317-1eaab46a0d33",
    "e8a698e9-c3e5-49bb-91d2-499b72e8d112",
    "68a4ecd7-5807-4ddd-9ffb-7ec93a352acc",
    "c449f4f8-b438-4b67-89f5-929ca43e93fd",
    "95e721c7-1969-45d9-ab89-d51a47903335",
    "fbfe8be4-92d2-4a0c-99c4-ce898c500381",
    "ee85a2ca-c728-4e23-a0a3-c11d1f3ed1e0",
    "173126b5-beb5-4bfd-a7f2-3494e4553081",
    "7eeaa1fc-e949-4eda-aa06-6cd364a2fe85"
  ],
  "camera": {
    "color": [
      48,
      48,
      48,
      255
    ],
    "fov": 45,
    "far": 10000,
    "near": 0.01,
    "wheelSpeed": 0.01,
    "wanderSpeed": 10,
    "enableAcceleration": true,
    "size": "__default_design__",
    "far2D": 10000,
    "near2D": 1,
    "wheelSpeed2D": 6,
    "iso": 0,
    "aperture": 19,
    "shutter": 7
  },
  "scene_view": {
    "isSceneLightOn": true,
    "output_device": "__default_design__"
  },
  "game-view": {
    "scaleValue": 62,
    "sliderValue": 29
  }
}
